change_detection_pytorch/__init__.py
change_detection_pytorch/__version__.py
change_detection_pytorch/V2/__init__.py
change_detection_pytorch/base/__init__.py
change_detection_pytorch/base/decoder.py
change_detection_pytorch/base/heads.py
change_detection_pytorch/base/initialization.py
change_detection_pytorch/base/model.py
change_detection_pytorch/base/modules.py
change_detection_pytorch/datasets/LEVIR_CD.py
change_detection_pytorch/datasets/SVCD.py
change_detection_pytorch/datasets/__init__.py
change_detection_pytorch/datasets/custom.py
change_detection_pytorch/datasets/transforms/__init__.py
change_detection_pytorch/datasets/transforms/albu.py
change_detection_pytorch/datasets/transforms/functional.py
change_detection_pytorch/deeplabv3/__init__.py
change_detection_pytorch/deeplabv3/decoder.py
change_detection_pytorch/deeplabv3/model.py
change_detection_pytorch/encoders/__init__.py
change_detection_pytorch/encoders/_base.py
change_detection_pytorch/encoders/_preprocessing.py
change_detection_pytorch/encoders/_utils.py
change_detection_pytorch/encoders/densenet.py
change_detection_pytorch/encoders/dpn.py
change_detection_pytorch/encoders/efficientnet.py
change_detection_pytorch/encoders/inceptionresnetv2.py
change_detection_pytorch/encoders/inceptionv4.py
change_detection_pytorch/encoders/mobilenet.py
change_detection_pytorch/encoders/resnet.py
change_detection_pytorch/encoders/senet.py
change_detection_pytorch/encoders/swin_transformer.py
change_detection_pytorch/encoders/swin_transformer_model.py
change_detection_pytorch/encoders/timm_efficientnet.py
change_detection_pytorch/encoders/timm_gernet.py
change_detection_pytorch/encoders/timm_mobilenetv3.py
change_detection_pytorch/encoders/timm_regnet.py
change_detection_pytorch/encoders/timm_res2net.py
change_detection_pytorch/encoders/timm_resnest.py
change_detection_pytorch/encoders/timm_sknet.py
change_detection_pytorch/encoders/timm_universal.py
change_detection_pytorch/encoders/vgg.py
change_detection_pytorch-0.1.4.dist-info/LICENSE
change_detection_pytorch-0.1.4.dist-info/METADATA
change_detection_pytorch-0.1.4.dist-info/WHEEL
change_detection_pytorch-0.1.4.dist-info/top_level.txt
change_detection_pytorch-0.1.4.dist-info/RECORD
