Metadata-Version: 2.1
Name: change-detection-pytorch
Version: 0.1.4
Summary: Change detection models with pre-trained backbones. Inspired by segmentation_models.pytorch.
Home-page: https://github.com/likyoo/change_detection.pytorch
Author: Kaiyu Li, Fulin Sun, Xudong Liu
Author-email: likyoo@sdust.edu.cn
License: MIT
Platform: UNKNOWN
Classifier: License :: OSI Approved :: MIT License
Classifier: Programming Language :: Python
Classifier: Programming Language :: Python :: 3
Classifier: Programming Language :: Python :: Implementation :: CPython
Classifier: Programming Language :: Python :: Implementation :: PyPy
Requires-Python: >=3.0.0
License-File: LICENSE
Requires-Dist: torchvision (>=0.5.0)
Requires-Dist: pretrainedmodels (==0.7.4)
Requires-Dist: efficientnet-pytorch (==0.6.3)
Requires-Dist: timm (==0.4.12)
Requires-Dist: albumentations
Provides-Extra: test
Requires-Dist: pytest ; extra == 'test'
